{"name":"游戏","slug":"游戏","count":1,"postlist":[{"title":"元宇宙初体验","uid":"63b7c208e07d1c6dac9a1c6cbbd7da50","slug":"metaverse","date":"2022-10-18T13:50:46.000Z","updated":"2022-10-18T14:32:37.026Z","comments":true,"path":"api/articles/metaverse.json","keywords":null,"cover":null,"text":"元宇宙初体验TODO： ","link":"","photos":[],"count_time":{"symbolsCount":12,"symbolsTime":"1 mins."},"categories":[{"name":"项目实践","slug":"项目实践","count":2,"path":"api/categories/项目实践.json"}],"tags":[{"name":"项目实践","slug":"项目实践","count":2,"path":"api/tags/项目实践.json"},{"name":"元宇宙","slug":"元宇宙","count":1,"path":"api/tags/元宇宙.json"},{"name":"Unity3D","slug":"Unity3D","count":1,"path":"api/tags/Unity3D.json"},{"name":"游戏","slug":"游戏","count":1,"path":"api/tags/游戏.json"},{"name":"c#","slug":"c","count":1,"path":"api/tags/c.json"}],"author":{"name":"卡卡罗特1874","slug":"卡卡罗特1874","avatar":"/image/20221018212951.jpg","link":"https://kakarot1874.com","description":"编程知识分享,互联网技术博客,互联网知识探讨和学习,喜欢无用之用的观点 —— 有好奇心的程序员.","socials":{"github":"","twitter":"","stackoverflow":"","wechat":"","qq":"","weibo":"","zhihu":"","csdn":"","juejin":"","customs":{"bilibili":{"icon":"/svg/bilibili.svg","link":"https://space.bilibili.com/23868503"},"github":{"icon":"/svg/github.svg","link":"https://github.com/kakarot1874"},"zhihu":{"icon":"/svg/zhihu.svg","link":"https://www.zhihu.com/people/zhou-le-sheng-1"}}}},"feature":true}]}